Metadata-Version: 2.1
Name: blip-gw
Version: 1.0.6
Summary: A bayesian pipeline for detecting stochastic backgrounds with LISA.
Home-page: UNKNOWN
Author: Sharan Banagiri
Author-email: banag002@umn.edu
License: UNKNOWN
Platform: UNKNOWN
Classifier: Programming Language :: Python :: 3
Classifier: License :: OSI Approved :: MIT License
Classifier: Operating System :: OS Independent
Requires-Dist: ChainConsumer (==0.31.0)
Requires-Dist: Cython (==0.29.16)
Requires-Dist: astropy (==4.0.1.post1)
Requires-Dist: corner (==2.0.1)
Requires-Dist: cycler (==0.10.0)
Requires-Dist: dynesty (==1.0.1)
Requires-Dist: healpy (==1.13.0)
Requires-Dist: kiwisolver (==1.2.0)
Requires-Dist: matplotlib (==3.2.1)
Requires-Dist: mpmath (==1.1.0)
Requires-Dist: numpy (==1.18.3)
Requires-Dist: pandas (==1.0.3)
Requires-Dist: patsy (==0.5.1)
Requires-Dist: pyparsing (==2.4.7)
Requires-Dist: python-dateutil (==2.8.1)
Requires-Dist: pytz (==2019.3)
Requires-Dist: scipy (==1.4.1)
Requires-Dist: six (==1.14.0)
Requires-Dist: statsmodels (==0.11.1)
Requires-Dist: sympy (==1.6)
